llama_index/embeddings/__init__.py
llama_index/embeddings/litellm/__init__.py
llama_index/embeddings/litellm/base.py
llama_index_embeddings_litellm-0.4.1.dist-info/METADATA
llama_index_embeddings_litellm-0.4.1.dist-info/WHEEL
llama_index_embeddings_litellm-0.4.1.dist-info/licenses/LICENSE
llama_index_embeddings_litellm-0.4.1.dist-info/RECORD
