Metadata-Version: 2.4
Name: llama-index-embeddings-litellm
Version: 0.4.1
Summary: llama-index embeddings litellm integration
Author-email: Your Name <you@example.com>
License-Expression: MIT
License-File: LICENSE
Requires-Python: <4.0,>=3.9
Requires-Dist: litellm<2,>=1.41.3
Requires-Dist: llama-index-core<0.15,>=0.13.0
